us/__init__.py
us/states.py
us/unitedstatesofamerica.py
us/version.py
us/cli/__init__.py
us/cli/states.py
us/tests/__init__.py
us/tests/test_us.py
us-3.2.0.dist-info/LICENSE
us-3.2.0.dist-info/METADATA
us-3.2.0.dist-info/WHEEL
us-3.2.0.dist-info/entry_points.txt
us-3.2.0.dist-info/top_level.txt
us-3.2.0.dist-info/RECORD
