Metadata-Version: 2.1
Name: us
Version: 3.2.0
Summary: US state meta information and other fun stuff
Author-email: Jeremy Carbaugh <jeremy@jcarbaugh.com>
License: Copyright (c) 2014, Sunlight Labs
Project-URL: Homepage, https://github.com/unitedstates/python-us/
Project-URL: Issue tracker, https://github.com/unitedstates/python-us/issues
Classifier: Programming Language :: Python
Classifier: Programming Language :: Python :: 3.8
Classifier: Programming Language :: Python :: 3.9
Classifier: Programming Language :: Python :: 3.10
Classifier: Programming Language :: Python :: 3.11
Classifier: Programming Language :: Python :: 3.12
Requires-Python: >=3.8
License-File: LICENSE
Requires-Dist: jellyfish
Provides-Extra: dev
Requires-Dist: flake8; extra == "dev"
Requires-Dist: black; extra == "dev"
Requires-Dist: pytest; extra == "dev"
Requires-Dist: pytz; extra == "dev"
